render_engine_fontawesome/__init__.py
render_engine_fontawesome/fontawesome.py
render_engine_fontawesome-2024.1.1a1.dist-info/METADATA
render_engine_fontawesome-2024.1.1a1.dist-info/WHEEL
render_engine_fontawesome-2024.1.1a1.dist-info/top_level.txt
render_engine_fontawesome-2024.1.1a1.dist-info/RECORD
