Metadata-Version: 2.1
Name: render-engine-fontawesome
Version: 2024.1.1a1
Summary: add the fontawesome iconset
Project-URL: homepage, https://github.com/kjaymiller/render_engine_fontawesome
Project-URL: repository, https://github.com/kjaymiller/render_engine_fontawesome
Project-URL: documentation, https://github.io/kjaymiller/render_engine_fontawesome
Requires-Dist: jinja2
Requires-Dist: render-engine >=2024.1.1a1
Provides-Extra: dev
Requires-Dist: pytest ; extra == 'dev'
Requires-Dist: ruff ; extra == 'dev'
